Workbook

Sheet Executive Summary
B2: Active Scenario: | C2: 1 | D2: =CHOOSE(C2, "Base Case", "Bull Case", "Bear Case") -> Base Case
D5: 2026E | E5: 2027E | F5: 2028E | G5: 2029E | H5: 2030E
B6: Total Revenue | D6: ='Income Statement'!F6 -> 441540.08 | E6: ='Income Statement'!G6 -> 468982.24 | F6: ='Income Statement'!H6 -> 498695.75 | G6: ='Income Statement'!I6 -> 530912.31 | H6: ='Income Statement'!J6 -> 565889.78
B7: Gross Margin % | D7: ='Income Statement'!F12/'Income Statement'!F6 -> 0.46691065 | E7: ='Income Statement'!G12/'Income Statement'!G6 -> 0.47218879 | F7: ='Income Statement'!H12/'Income Statement'!H6 -> 0.47763215 | G7: ='Income Statement'!I12/'Income Statement'!I6 -> 0.48323297 | H7: ='Income Statement'!J12/'Income Statement'!J6 -> 0.48898217
B8: Net Income | D8: ='Income Statement'!F21 -> 117456.15 | E8: ='Income Statement'!G21 -> 126840.69 | F8: ='Income Statement'!H21 -> 137162.56 | G8: ='Income Statement'!I21 -> 148526.69 | H8: ='Income Statement'!J21 -> 161050.3
B9: Ending Cash Balance | D9: ='Cash Flow Statement'!F20 -> 184824.04 | E9: ='Cash Flow Statement'!G20 -> 184824.04 | F9: ='Cash Flow Statement'!H20 -> 184824.04 | G9: ='Cash Flow Statement'!I20 -> 184824.04 | H9: ='Cash Flow Statement'!J20 -> 184824.04

Sheet Assumptions
F2: 2026E | G2: 2027E | H2: 2028E | I2: 2029E | J2: 2030E
B4: Product Revenue Growth % | F4: =CHOOSE('Executive Summary'!$C$2, 0.04, 0.08, 0.01) -> 0.04 | G4: =CHOOSE('Executive Summary'!$C$2, 0.04, 0.08, 0.01) -> 0.04 | H4: =CHOOSE('Executive Summary'!$C$2, 0.04, 0.08, 0.01) -> 0.04 | I4: =CHOOSE('Executive Summary'!$C$2, 0.04, 0.08, 0.01) -> 0.04 | J4: =CHOOSE('Executive Summary'!$C$2, 0.04, 0.08, 0.01) -> 0.04
B5: Service Revenue Growth % | F5: =CHOOSE('Executive Summary'!$C$2, 0.12, 0.18, 0.05) -> 0.12 | G5: =CHOOSE('Executive Summary'!$C$2, 0.12, 0.18, 0.05) -> 0.12 | H5: =CHOOSE('Executive Summary'!$C$2, 0.12, 0.18, 0.05) -> 0.12 | I5: =CHOOSE('Executive Summary'!$C$2, 0.12, 0.18, 0.05) -> 0.12 | J5: =CHOOSE('Executive Summary'!$C$2, 0.12, 0.18, 0.05) -> 0.12
B7: Product COGS Margin % | F7: 0.63 | G7: 0.63 | H7: 0.63 | I7: 0.63 | J7: 0.63
B8: Service COGS Margin % | F8: 0.28 | G8: 0.28 | H8: 0.28 | I8: 0.28 | J8: 0.28
B9: R&D as % of Total Revenue | F9: 0.08 | G9: 0.08 | H9: 0.08 | I9: 0.08 | J9: 0.08
B10: SG&A as % of Total Revenue | F10: 0.07 | G10: 0.07 | H10: 0.07 | I10: 0.07 | J10: 0.07
B11: Effective Tax Rate % | F11: 0.16 | G11: 0.16 | H11: 0.16 | I11: 0.16 | J11: 0.16
B13: Accounts Receivable (% of Total Revenue) | F13: 0.16 | G13: 0.16 | H13: 0.16 | I13: 0.16 | J13: 0.16
B14: Inventory (% of Product COGS) | F14: 0.04 | G14: 0.04 | H14: 0.04 | I14: 0.04 | J14: 0.04
B15: Accounts Payable (% of Total COGS) | F15: 0.3 | G15: 0.3 | H15: 0.3 | I15: 0.3 | J15: 0.3
B16: CapEx (% of Total Revenue) | F16: 0.03 | G16: 0.03 | H16: 0.03 | I16: 0.03 | J16: 0.03
B17: Depreciation (% of Beginning PP&E) | F17: 0.05 | G17: 0.05 | H17: 0.05 | I17: 0.05 | J17: 0.05

Sheet Income Statement
C2: 2023 | D2: 2024 | E2: 2025 | F2: 2026E | G2: 2026E | H2: 2026E | I2: 2026E | J2: 2026E
B4: Net Sales: Products | C4: 298085 | D4: 294866 | E4: 307003 | F4: =E4*(1+Assumptions!F4) -> 319283.12 | G4: =F4*(1+Assumptions!G4) -> 332054.44 | H4: =G4*(1+Assumptions!H4) -> 345336.62 | I4: =H4*(1+Assumptions!I4) -> 359150.09 | J4: =I4*(1+Assumptions!J4) -> 373516.09
B5: Net Sales: Services | C5: 85200 | D5: 96169 | E5: 109158 | F5: =E5*(1+Assumptions!F5) -> 122256.96 | G5: =F5*(1+Assumptions!G5) -> 136927.8 | H5: =G5*(1+Assumptions!H5) -> 153359.13 | I5: =H5*(1+Assumptions!I5) -> 171762.23 | J5: =I5*(1+Assumptions!J5) -> 192373.69
B6: Total Net Sales | C6: =C4+C5 -> 383285 | D6: =D4+D5 -> 391035 | E6: =E4+E5 -> 416161 | F6: =F4+F5 -> 441540.08 | G6: =G4+G5 -> 468982.24 | H6: =H4+H5 -> 498695.75 | I6: =I4+I5 -> 530912.31 | J6: =J4+J5 -> 565889.78
B8: Cost of Sales: Products | C8: 192000 | D8: 185233 | E8: 194116 | F8: =F4*Assumptions!F7 -> 201148.37 | G8: =G4*Assumptions!G7 -> 209194.3 | H8: =H4*Assumptions!H7 -> 217562.07 | I8: =I4*Assumptions!I7 -> 226264.56 | J8: =J4*Assumptions!J7 -> 235315.14
B9: Cost of Sales: Services | C9: 24000 | D9: 26000 | E9: 30000 | F9: =F5*Assumptions!F8 -> 34231.949 | G9: =G5*Assumptions!G8 -> 38339.783 | H9: =H5*Assumptions!H8 -> 42940.557 | I9: =I5*Assumptions!I8 -> 48093.423 | J9: =J5*Assumptions!J8 -> 53864.634
B10: Total Cost of Sales | C10: =C8+C9 -> 216000 | D10: =D8+D9 -> 211233 | E10: =E8+E9 -> 224116 | F10: =F8+F9 -> 235380.31 | G10: =G8+G9 -> 247534.08 | H10: =H8+H9 -> 260502.63 | I10: =I8+I9 -> 274357.98 | J10: =J8+J9 -> 289179.77
B12: Gross Margin | C12: =C6-C10 -> 167285 | D12: =D6-D10 -> 179802 | E12: =E6-E10 -> 192045 | F12: =F6-F10 -> 206159.77 | G12: =G6-G10 -> 221448.16 | H12: =H6-H10 -> 238193.12 | I12: =I6-I10 -> 256554.34 | J12: =J6-J10 -> 276710.01
B13: Research and Development (R&D) | C13: 29915 | D13: 31370 | E13: 33500 | F13: =F6*Assumptions!F9 -> 35323.206 | G13: =G6*Assumptions!G9 -> 37518.579 | H13: =H6*Assumptions!H9 -> 39895.66 | I13: =I6*Assumptions!I9 -> 42472.985 | J13: =J6*Assumptions!J9 -> 45271.183
B14: Selling, General & Administrative (SG&A) | C14: 24932 | D14: 26251 | E14: 28100 | F14: =F6*Assumptions!F10 -> 30907.806 | G14: =G6*Assumptions!G10 -> 32828.757 | H14: =H6*Assumptions!H10 -> 34908.703 | I14: =I6*Assumptions!I10 -> 37163.862 | J14: =J6*Assumptions!J10 -> 39612.285
B15: Total Operating Expenses | C15: =C13+C14 -> 54847 | D15: =D13+D14 -> 57621 | E15: =E13+E14 -> 61600 | F15: =F13+F14 -> 66231.012 | G15: =G13+G14 -> 70347.336 | H15: =H13+H14 -> 74804.363 | I15: =I13+I14 -> 79636.847 | J15: =J13+J14 -> 84883.468
B17: Operating Income (EBIT) | C17: =C12-C15 -> 112438 | D17: =D12-D15 -> 122181 | E17: =E12-E15 -> 130445 | F17: =F12-F15 -> 139928.75 | G17: =G12-G15 -> 151100.82 | H17: =H12-H15 -> 163388.76 | I17: =I12-I15 -> 176917.49 | J17: =J12-J15 -> 191826.55
B18: Other Income/(Expense), Net | C18: -300 | D18: -150 | E18: -100 | F18: =E18 -> -100 | G18: =F18 -> -100 | H18: =G18 -> -100 | I18: =H18 -> -100 | J18: =I18 -> -100
B19: Provision for Income Taxes | C19: 16700 | D19: 18200 | E19: 21500 | F19: =F20*Assumptions!F11 -> 22372.601 | G19: =G20*Assumptions!G11 -> 24160.131 | H19: =H20*Assumptions!H11 -> 26126.202 | I19: =I20*Assumptions!I11 -> 28290.798 | J19: =J20*Assumptions!J11 -> 30676.247
B20: Income Before Provison for Income Taxes | C20: =C17+C18 -> 112138 | D20: =D17+D18 -> 122031 | E20: =E17+E18 -> 130345 | F20: =F17+F18 -> 139828.75 | G20: =G17+G18 -> 151000.82 | H20: =H17+H18 -> 163288.76 | I20: =I17+I18 -> 176817.49 | J20: =J17+J18 -> 191726.55
B21: Net Income | C21: =C20-C19 -> 95438 | D21: =D20-D19 -> 103831 | E21: =E20-E19 -> 108845 | F21: =F20-F19 -> 117456.15 | G21: =G20-G19 -> 126840.69 | H21: =H20-H19 -> 137162.56 | I21: =I20-I19 -> 148526.69 | J21: =J20-J19 -> 161050.3

Sheet Balance Sheet
C2: 2023 | D2: 2024 | E2: 2025 | F2: 2026E | G2: 2027E | H2: 2028E | I2: 2029E | J2: 20230E
B4: Cash and Cash Equivalents | C4: 61555 | D4: 65171 | E4: 75000 | F4: ='Cash Flow Statement'!F21 -> 0 | G4: ='Cash Flow Statement'!G21 -> 0 | H4: ='Cash Flow Statement'!H21 -> 0 | I4: ='Cash Flow Statement'!I21 -> 0 | J4: ='Cash Flow Statement'!J21 -> 0
B5: Accounts Receivables | C5: 60985 | D5: 66243 | E5: 70000 | F5: ='Income Statement'!F6*Assumptions!F13 -> 70646.413 | G5: ='Income Statement'!G6*Assumptions!G13 -> 75037.158 | H5: ='Income Statement'!H6*Assumptions!H13 -> 79791.321 | I5: ='Income Statement'!I6*Assumptions!I13 -> 84945.97 | J5: ='Income Statement'!J6*Assumptions!J13 -> 90542.366
B6: Inventories | C6: 6331 | D6: 7286 | E6: 8000 | F6: ='Income Statement'!F10*Assumptions!F14 -> 9415.2126 | G6: ='Income Statement'!G10*Assumptions!G14 -> 9901.3633 | H6: ='Income Statement'!H10*Assumptions!H14 -> 10420.105 | I6: ='Income Statement'!I10*Assumptions!I14 -> 10974.319 | J6: ='Income Statement'!J10*Assumptions!J14 -> 11567.191
B7: Total Current Assets | C7: =C4+C5+C6 -> 128871 | D7: =D4+D5+D6 -> 138700 | E7: =E4+E5+E6 -> 153000 | F7: =F4+F5+F6 -> 80061.625 | G7: =G4+G5+G6 -> 84938.522 | H7: =H4+H5+H6 -> 90211.426 | I7: =I4+I5+I6 -> 95920.289 | J7: =J4+J5+J6 -> 102109.56
B8: Property, Plant & Equipment (PP&E), Net | C8: 223712 | D8: 226280 | E8: 235000 | F8: =E8+'Cash Flow Statement'!F11-'Cash Flow Statement'!F5 -> 210003.8 | G8: =F8+'Cash Flow Statement'!G11-'Cash Flow Statement'!G5 -> 185434.14 | H8: =G8+'Cash Flow Statement'!H11-'Cash Flow Statement'!H5 -> 161201.56 | I8: =H8+'Cash Flow Statement'!I11-'Cash Flow Statement'!I5 -> 137214.11 | J8: =I8+'Cash Flow Statement'!J11-'Cash Flow Statement'!J5 -> 113376.71
B9: Total Assets | C9: =C7+C8 -> 352583 | D9: =D7+D8 -> 364980 | E9: =E7+E8 -> 388000 | F9: =F7+F8 -> 290065.42 | G9: =G7+G8 -> 270372.66 | H9: =H7+H8 -> 251412.99 | I9: =I7+I8 -> 233134.4 | J9: =J7+J8 -> 215486.27
B11: Accounts Payable | C11: 62611 | D11: 58110 | E11: 65000 | F11: ='Income Statement'!F10*Assumptions!F15 -> 70614.094 | G11: ='Income Statement'!G10*Assumptions!G15 -> 74260.225 | H11: ='Income Statement'!H10*Assumptions!H15 -> 78150.789 | I11: ='Income Statement'!I10*Assumptions!I15 -> 82307.394 | J11: ='Income Statement'!J10*Assumptions!J15 -> 86753.931
B12: Commercial paper & Short Term Debt | C12: 59888 | D12: 60000 | E12: 62285 | F12: =E12 -> 62285 | G12: =F12 -> 62285 | H12: =G12 -> 62285 | I12: =H12 -> 62285 | J12: =I12 -> 62285
B13: Total Current Liabilities | C13: =C11+C12 -> 122499 | D13: =D11+D12 -> 118110 | E13: =E11+E12 -> 127285 | F13: =F11+F12 -> 132899.09 | G13: =G11+G12 -> 136545.22 | H13: =H11+H12 -> 140435.79 | I13: =I11+I12 -> 144592.39 | J13: =J11+J12 -> 149038.93
B14: Long Term Debt | C14: 167922 | D14: 175000 | E14: 170000 | F14: =E14 -> 170000 | G14: =F14 -> 170000 | H14: =G14 -> 170000 | I14: =H14 -> 170000 | J14: =I14 -> 170000
B15: Total Liabilities | C15: =C13+C14 -> 290421 | D15: =D13+D14 -> 293110 | E15: =E13+E14 -> 297285 | F15: =F13+F14 -> 302899.09 | G15: =G13+G14 -> 306545.22 | H15: =H13+H14 -> 310435.79 | I15: =I13+I14 -> 314592.39 | J15: =J13+J14 -> 319038.93
B17: Common Stock & Retained Earnings | C17: 62162 | D17: 71870 | E17: 90715 | F17: =E17+'Income Statement'!F21 -> 208171.15 | G17: =F17+'Income Statement'!G21 -> 335011.84 | H17: =G17+'Income Statement'!H21 -> 472174.4 | I17: =H17+'Income Statement'!I21 -> 620701.09 | J17: =I17+'Income Statement'!J21 -> 781751.39
B18: Total Shareholders' Equity | C18: =C17 -> 62162 | D18: =D17 -> 71870 | E18: =E17 -> 90715 | F18: =F17 -> 208171.15 | G18: =G17 -> 335011.84 | H18: =H17 -> 472174.4 | I18: =I17 -> 620701.09 | J18: =J17 -> 781751.39
B20: Total Liabilities & Equity | C20: =C15+C18 -> 352583 | D20: =D15+D18 -> 364980 | E20: =E15+E18 -> 388000 | F20: =F15+F18 -> 511070.25 | G20: =G15+G18 -> 641557.07 | H20: =H15+H18 -> 782610.19 | I20: =I15+I18 -> 935293.49 | J20: =J15+J18 -> 1100790.3
B21: Balance Check (Zero out) | C21: =C9-C20 -> 0 | D21: =D9-D20 -> 0 | E21: =E9-E20 -> 0 | F21: =F9-F20 -> -221004.82 | G21: =G9-G20 -> -371184.41 | H21: =H9-H20 -> -531197.2 | I21: =I9-I20 -> -702159.08 | J21: =J9-J20 -> -885304.05

Sheet Cash Flow Statement
C2: 2023 | D2: 2024 | E2: 2025 | F2: 2026E | G2: 2027E | H2: 2028E | I2: 2029E | J2: 2030E
B4: Net Income | D4: ='Income Statement'!D21 -> 103831 | E4: ='Income Statement'!E21 -> 108845 | F4: ='Income Statement'!F21 -> 117456.15 | G4: ='Income Statement'!G21 -> 126840.69 | H4: ='Income Statement'!H21 -> 137162.56 | I4: ='Income Statement'!I21 -> 148526.69 | J4: ='Income Statement'!J21 -> 161050.3
B5: Depriciation and Amortization | D5: 11500 | E5: 12000 | F5: ='Balance Sheet'!E8*Assumptions!F17 -> 11750 | G5: ='Balance Sheet'!F8*Assumptions!G17 -> 10500.19 | H5: ='Balance Sheet'!G8*Assumptions!H17 -> 9271.707 | I5: ='Balance Sheet'!H8*Assumptions!I17 -> 8060.078 | J5: ='Balance Sheet'!I8*Assumptions!J17 -> 6860.7057
B6: Change in Accounts Receivable | D6: ='Balance Sheet'!C5-'Balance Sheet'!D5 -> -5258 | E6: ='Balance Sheet'!D5-'Balance Sheet'!E5 -> -3757 | F6: ='Balance Sheet'!E5-'Balance Sheet'!F5 -> -646.4128 | G6: ='Balance Sheet'!F5-'Balance Sheet'!G5 -> -4390.7456 | H6: ='Balance Sheet'!G5-'Balance Sheet'!H5 -> -4754.1621 | I6: ='Balance Sheet'!H5-'Balance Sheet'!I5 -> -5154.6497 | J6: ='Balance Sheet'!I5-'Balance Sheet'!J5 -> -5596.3953
B7: Change in Inventories | D7: ='Balance Sheet'!C6-'Balance Sheet'!D6 -> -955 | E7: ='Balance Sheet'!D6-'Balance Sheet'!E6 -> -714 | F7: ='Balance Sheet'!E6-'Balance Sheet'!F6 -> -1415.2126 | G7: ='Balance Sheet'!F6-'Balance Sheet'!G6 -> -486.15074 | H7: ='Balance Sheet'!G6-'Balance Sheet'!H6 -> -518.74184 | I7: ='Balance Sheet'!H6-'Balance Sheet'!I6 -> -554.21399 | J7: ='Balance Sheet'!I6-'Balance Sheet'!J6 -> -592.87172
B8: Change in Accounts Payable | D8: ='Balance Sheet'!D11-'Balance Sheet'!C11 -> -4501 | E8: ='Balance Sheet'!E11-'Balance Sheet'!D11 -> 6890 | F8: ='Balance Sheet'!F11-'Balance Sheet'!E11 -> 5614.0943 | G8: ='Balance Sheet'!G11-'Balance Sheet'!F11 -> 3646.1305 | H8: ='Balance Sheet'!H11-'Balance Sheet'!G11 -> 3890.5638 | I8: ='Balance Sheet'!I11-'Balance Sheet'!H11 -> 4156.6049 | J8: ='Balance Sheet'!J11-'Balance Sheet'!I11 -> 4446.5379
B9: Total Cash Flow from Operations | D9: =SUM(D4,D8) -> 99330 | E9: =SUM(E4,E8) -> 115735 | F9: =SUM(F4,F8) -> 123070.25 | G9: =SUM(G4,G8) -> 130486.82 | H9: =SUM(H4,H8) -> 141053.12 | I9: =SUM(I4,I8) -> 152683.3 | J9: =SUM(J4,J8) -> 165496.84
B11: Capital Expenditure | D11: -10500 | E11: -12220 | F11: =-('Income Statement'!F6*Assumptions!F16) -> -13246.202 | G11: =-('Income Statement'!G6*Assumptions!G16) -> -14069.467 | H11: =-('Income Statement'!H6*Assumptions!H16) -> -14960.873 | I11: =-('Income Statement'!I6*Assumptions!I16) -> -15927.369 | J11: =-('Income Statement'!J6*Assumptions!J16) -> -16976.694
B12: Total Cash Flow from Investing | D12: =D11 -> -10500 | E12: =E11 -> -12220 | F12: =F11 -> -13246.202 | G12: =G11 -> -14069.467 | H12: =H11 -> -14960.873 | I12: =I11 -> -15927.369 | J12: =J11 -> -16976.694
B14: Change in Short-Term Debt | D14: ='Balance Sheet'!D12-'Balance Sheet'!C12 -> 112 | E14: ='Balance Sheet'!E12-'Balance Sheet'!D12 -> 2285 | F14: ='Balance Sheet'!F12-'Balance Sheet'!E12 -> 0 | G14: ='Balance Sheet'!G12-'Balance Sheet'!F12 -> 0 | H14: ='Balance Sheet'!H12-'Balance Sheet'!G12 -> 0 | I14: ='Balance Sheet'!I12-'Balance Sheet'!H12 -> 0 | J14: ='Balance Sheet'!J12-'Balance Sheet'!I12 -> 0
B15: Change in Long-Term Debt | D15: ='Balance Sheet'!D14-'Balance Sheet'!C14 -> 7078 | E15: ='Balance Sheet'!E14-'Balance Sheet'!D14 -> -5000 | F15: ='Balance Sheet'!F14-'Balance Sheet'!E14 -> 0 | G15: ='Balance Sheet'!G14-'Balance Sheet'!F14 -> 0 | H15: ='Balance Sheet'!H14-'Balance Sheet'!G14 -> 0 | I15: ='Balance Sheet'!I14-'Balance Sheet'!H14 -> 0 | J15: ='Balance Sheet'!J14-'Balance Sheet'!I14 -> 0
B16: Total Cash Flow from Financing | D16: =SUM(D14,D15) -> 7190 | E16: =SUM(E14,E15) -> -2715 | F16: =SUM(F14,F15) -> 0 | G16: =SUM(G14,G15) -> 0 | H16: =SUM(H14,H15) -> 0 | I16: =SUM(I14,I15) -> 0 | J16: =SUM(J14,J15) -> 0
B18: Net Change in Cash | D18: =SUM(D9,D12,D16) -> 96020 | E18: =SUM(E9,E12,E16) -> 100800 | F18: =SUM(F9,F12,F16) -> 109824.04 | G18: =SUM(G9,G12,G16) -> 116417.35 | H18: =SUM(H9,H12,H16) -> 126092.25 | I18: =SUM(I9,I12,I16) -> 136755.93 | J18: =SUM(J9,J12,J16) -> 148520.14
B19: Cash at Beginning of Year | D19: ='Balance Sheet'!C4 -> 61555 | E19: ='Balance Sheet'!D4 -> 65171 | F19: ='Balance Sheet'!E4 -> 75000 | G19: ='Balance Sheet'!F4 -> 75000 | H19: ='Balance Sheet'!G4 -> 0 | I19: ='Balance Sheet'!H4 -> 0 | J19: ='Balance Sheet'!I4 -> 0
B20: Cash at End of Year | D20: =SUM(D18,D19) -> 157575 | E20: =SUM(E18,E19) -> 165971 | F20: =SUM(F18,F19) -> 184824.04 | G20: =SUM(G18,G19) -> 184824.04 | H20: =SUM(H18,H19) -> 126092.25 | I20: =SUM(I18,I19) -> 136755.93 | J20: =SUM(J18,J19) -> 148520.14
B21: Reconcillation Check | D21: =D20-'Balance Sheet'!D4 -> 92404 | E21: =E20-'Balance Sheet'!E4 -> 90971 | F21: =F20-'Balance Sheet'!F4 -> 0 | G21: =G20-'Balance Sheet'!G4 -> 0 | H21: =H20-'Balance Sheet'!H4 -> 0 | I21: =I20-'Balance Sheet'!I4 -> 0 | J21: =J20-'Balance Sheet'!J4 -> 0
